{"_ts":[1567386530,1567472795,1567647124],"_r":{"breakdown":{"html":{"bytes":[130144,127681,111321],"requests":[78,82,72]},"js":{"bytes":[885403,801366,932634],"requests":[76,75,77]},"css":{"bytes":[43210,43210,43204],"requests":[5,5,5]},"image":{"bytes":[2343869,2371373,2404684],"requests":[131,143,147]},"flash":{"bytes":[0,0,0],"requests":[0,0,0]},"font":{"bytes":[111860,111860,111860],"requests":[7,7,7]},"video":{"bytes":[0,0,0],"requests":[0,0,0]},"other":{"bytes":[52809,63313,58724],"requests":[47,46,44]}},"date":[1567386530,1567472795,1567647124],"domElements":[2638,2639,2640],"domInteractive":[1284,1181,1120],"firstPaint":[1142.5500000041,1164.1999999993,1135.680000003],"fullyLoaded":[17399,17089,17398],"id":["190902_WF_46b7242b26629fa2f55eea2baee7b966","190903_V0_61d5e0feac01bf4d2ffffd09603cf439","190905_HB_e803d3d2b6475f7aa65cf3e2404e410f"],"loadTime":[2737,2525,2401],"render":[1100,1200,1200],"SpeedIndex":[3632,3497,3433],"TTFB":[204,252,216],"videoFrames":[[{"_i":"ms_000000.jpg","_t":0,"_vc":0},{"_i":"ms_001100.jpg","_t":1100,"_vc":33},{"_i":"ms_001400.jpg","_t":1400,"_vc":33},{"_i":"ms_002100.jpg","_t":2100,"_vc":33},{"_i":"ms_002200.jpg","_t":2200,"_vc":39},{"_i":"ms_002400.jpg","_t":2400,"_vc":40},{"_i":"ms_002600.jpg","_t":2600,"_vc":63},{"_i":"ms_002900.jpg","_t":2900,"_vc":63},{"_i":"ms_003100.jpg","_t":3100,"_vc":63},{"_i":"ms_003500.jpg","_t":3500,"_vc":63},{"_i":"ms_003600.jpg","_t":3600,"_vc":63},{"_i":"ms_003800.jpg","_t":3800,"_vc":63},{"_i":"ms_004300.jpg","_t":4300,"_vc":68},{"_i":"ms_004400.jpg","_t":4400,"_vc":69},{"_i":"ms_005300.jpg","_t":5300,"_vc":83},{"_i":"ms_005400.jpg","_t":5400,"_vc":79},{"_i":"ms_005500.jpg","_t":5500,"_vc":83},{"_i":"ms_005600.jpg","_t":5600,"_vc":84},{"_i":"ms_005700.jpg","_t":5700,"_vc":93},{"_i":"ms_005900.jpg","_t":5900,"_vc":93},{"_i":"ms_006100.jpg","_t":6100,"_vc":94},{"_i":"ms_006500.jpg","_t":6500,"_vc":93},{"_i":"ms_007800.jpg","_t":7800,"_vc":93},{"_i":"ms_008100.jpg","_t":8100,"_vc":93},{"_i":"ms_008600.jpg","_t":8600,"_vc":93},{"_i":"ms_009100.jpg","_t":9100,"_vc":94},{"_i":"ms_009500.jpg","_t":9500,"_vc":94},{"_i":"ms_010300.jpg","_t":10300,"_vc":94},{"_i":"ms_010700.jpg","_t":10700,"_vc":94},{"_i":"ms_011300.jpg","_t":11300,"_vc":94},{"_i":"ms_011700.jpg","_t":11700,"_vc":94},{"_i":"ms_012100.jpg","_t":12100,"_vc":95},{"_i":"ms_012600.jpg","_t":12600,"_vc":95},{"_i":"ms_013000.jpg","_t":13000,"_vc":95},{"_i":"ms_013600.jpg","_t":13600,"_vc":99},{"_i":"ms_015600.jpg","_t":15600,"_vc":99},{"_i":"ms_016900.jpg","_t":16900,"_vc":100},{"_i":"ms_017600.jpg","_t":17600,"_vc":99},{"_i":"ms_019600.jpg","_t":19600,"_vc":100}],[{"_i":"ms_000000.jpg","_t":0,"_vc":0},{"_i":"ms_001200.jpg","_t":1200,"_vc":33},{"_i":"ms_001300.jpg","_t":1300,"_vc":33},{"_i":"ms_001900.jpg","_t":1900,"_vc":33},{"_i":"ms_002000.jpg","_t":2000,"_vc":39},{"_i":"ms_002100.jpg","_t":2100,"_vc":62},{"_i":"ms_002200.jpg","_t":2200,"_vc":62},{"_i":"ms_002400.jpg","_t":2400,"_vc":62},{"_i":"ms_002900.jpg","_t":2900,"_vc":63},{"_i":"ms_003000.jpg","_t":3000,"_vc":63},{"_i":"ms_003100.jpg","_t":3100,"_vc":63},{"_i":"ms_003800.jpg","_t":3800,"_vc":62},{"_i":"ms_004100.jpg","_t":4100,"_vc":62},{"_i":"ms_004500.jpg","_t":4500,"_vc":63},{"_i":"ms_004600.jpg","_t":4600,"_vc":63},{"_i":"ms_004700.jpg","_t":4700,"_vc":63},{"_i":"ms_004800.jpg","_t":4800,"_vc":63},{"_i":"ms_004900.jpg","_t":4900,"_vc":63},{"_i":"ms_005000.jpg","_t":5000,"_vc":63},{"_i":"ms_005100.jpg","_t":5100,"_vc":64},{"_i":"ms_005200.jpg","_t":5200,"_vc":71},{"_i":"ms_005300.jpg","_t":5300,"_vc":83},{"_i":"ms_005400.jpg","_t":5400,"_vc":80},{"_i":"ms_005500.jpg","_t":5500,"_vc":81},{"_i":"ms_005600.jpg","_t":5600,"_vc":88},{"_i":"ms_005700.jpg","_t":5700,"_vc":92},{"_i":"ms_006100.jpg","_t":6100,"_vc":92},{"_i":"ms_006200.jpg","_t":6200,"_vc":92},{"_i":"ms_006700.jpg","_t":6700,"_vc":92},{"_i":"ms_007000.jpg","_t":7000,"_vc":92},{"_i":"ms_007500.jpg","_t":7500,"_vc":93},{"_i":"ms_008100.jpg","_t":8100,"_vc":93},{"_i":"ms_008500.jpg","_t":8500,"_vc":93},{"_i":"ms_009300.jpg","_t":9300,"_vc":94},{"_i":"ms_009800.jpg","_t":9800,"_vc":94},{"_i":"ms_010000.jpg","_t":10000,"_vc":94},{"_i":"ms_010500.jpg","_t":10500,"_vc":94},{"_i":"ms_011000.jpg","_t":11000,"_vc":95},{"_i":"ms_011500.jpg","_t":11500,"_vc":94},{"_i":"ms_012000.jpg","_t":12000,"_vc":99},{"_i":"ms_012700.jpg","_t":12700,"_vc":99},{"_i":"ms_013000.jpg","_t":13000,"_vc":99},{"_i":"ms_013500.jpg","_t":13500,"_vc":100},{"_i":"ms_015600.jpg","_t":15600,"_vc":100},{"_i":"ms_017600.jpg","_t":17600,"_vc":100}],[{"_i":"ms_000000.jpg","_t":0,"_vc":0},{"_i":"ms_001200.jpg","_t":1200,"_vc":33},{"_i":"ms_001600.jpg","_t":1600,"_vc":33},{"_i":"ms_001800.jpg","_t":1800,"_vc":33},{"_i":"ms_001900.jpg","_t":1900,"_vc":63},{"_i":"ms_002000.jpg","_t":2000,"_vc":63},{"_i":"ms_002300.jpg","_t":2300,"_vc":63},{"_i":"ms_002500.jpg","_t":2500,"_vc":63},{"_i":"ms_003200.jpg","_t":3200,"_vc":63},{"_i":"ms_003300.jpg","_t":3300,"_vc":63},{"_i":"ms_003400.jpg","_t":3400,"_vc":63},{"_i":"ms_003700.jpg","_t":3700,"_vc":64},{"_i":"ms_003900.jpg","_t":3900,"_vc":64},{"_i":"ms_004900.jpg","_t":4900,"_vc":69},{"_i":"ms_005000.jpg","_t":5000,"_vc":81},{"_i":"ms_005100.jpg","_t":5100,"_vc":78},{"_i":"ms_005200.jpg","_t":5200,"_vc":81},{"_i":"ms_005300.jpg","_t":5300,"_vc":93},{"_i":"ms_005400.jpg","_t":5400,"_vc":93},{"_i":"ms_005600.jpg","_t":5600,"_vc":93},{"_i":"ms_005700.jpg","_t":5700,"_vc":93},{"_i":"ms_006200.jpg","_t":6200,"_vc":94},{"_i":"ms_006500.jpg","_t":6500,"_vc":93},{"_i":"ms_007000.jpg","_t":7000,"_vc":93},{"_i":"ms_007500.jpg","_t":7500,"_vc":93},{"_i":"ms_008000.jpg","_t":8000,"_vc":94},{"_i":"ms_008500.jpg","_t":8500,"_vc":94},{"_i":"ms_009000.jpg","_t":9000,"_vc":94},{"_i":"ms_009500.jpg","_t":9500,"_vc":94},{"_i":"ms_010000.jpg","_t":10000,"_vc":94},{"_i":"ms_010900.jpg","_t":10900,"_vc":94},{"_i":"ms_011000.jpg","_t":11000,"_vc":94},{"_i":"ms_011600.jpg","_t":11600,"_vc":95},{"_i":"ms_012000.jpg","_t":12000,"_vc":95},{"_i":"ms_012500.jpg","_t":12500,"_vc":94},{"_i":"ms_013000.jpg","_t":13000,"_vc":97},{"_i":"ms_013600.jpg","_t":13600,"_vc":98},{"_i":"ms_014000.jpg","_t":14000,"_vc":98},{"_i":"ms_014500.jpg","_t":14500,"_vc":97},{"_i":"ms_015100.jpg","_t":15100,"_vc":97},{"_i":"ms_015500.jpg","_t":15500,"_vc":97},{"_i":"ms_016000.jpg","_t":16000,"_vc":99},{"_i":"ms_016500.jpg","_t":16500,"_vc":99},{"_i":"ms_017000.jpg","_t":17000,"_vc":99},{"_i":"ms_017500.jpg","_t":17500,"_vc":99},{"_i":"ms_017700.jpg","_t":17700,"_vc":100}]],"visualComplete":[16900,13500,17700],"lighthouse":[57,57,57],"pagespeed":[70,70,70]}}