{"_ts":[1575253197],"_r":{"breakdown":{"html":{"bytes":[104277],"requests":[59]},"js":{"bytes":[883246],"requests":[76]},"css":{"bytes":[46112],"requests":[3]},"image":{"bytes":[340229],"requests":[115]},"flash":{"bytes":[0],"requests":[0]},"font":{"bytes":[0],"requests":[0]},"video":{"bytes":[0],"requests":[0]},"other":{"bytes":[34422],"requests":[44]}},"date":[1575253197],"domElements":[2585],"domInteractive":[1202],"firstPaint":[1142.5100000051],"fullyLoaded":[12957],"id":["191202_JF_3886fa33873bb087f3033b3567a90a8d"],"loadTime":[2387],"render":[1200],"SpeedIndex":[2864],"TTFB":[238],"videoFrames":[[{"_i":"ms_000000.jpg","_t":0,"_vc":0},{"_i":"ms_001200.jpg","_t":1200,"_vc":42},{"_i":"ms_001300.jpg","_t":1300,"_vc":42},{"_i":"ms_001600.jpg","_t":1600,"_vc":42},{"_i":"ms_001700.jpg","_t":1700,"_vc":42},{"_i":"ms_001800.jpg","_t":1800,"_vc":42},{"_i":"ms_001900.jpg","_t":1900,"_vc":40},{"_i":"ms_002000.jpg","_t":2000,"_vc":40},{"_i":"ms_002100.jpg","_t":2100,"_vc":50},{"_i":"ms_002400.jpg","_t":2400,"_vc":50},{"_i":"ms_002800.jpg","_t":2800,"_vc":50},{"_i":"ms_002900.jpg","_t":2900,"_vc":51},{"_i":"ms_003000.jpg","_t":3000,"_vc":51},{"_i":"ms_003300.jpg","_t":3300,"_vc":51},{"_i":"ms_003800.jpg","_t":3800,"_vc":53},{"_i":"ms_003900.jpg","_t":3900,"_vc":55},{"_i":"ms_004000.jpg","_t":4000,"_vc":64},{"_i":"ms_004100.jpg","_t":4100,"_vc":69},{"_i":"ms_004200.jpg","_t":4200,"_vc":87},{"_i":"ms_004300.jpg","_t":4300,"_vc":93},{"_i":"ms_004800.jpg","_t":4800,"_vc":94},{"_i":"ms_004900.jpg","_t":4900,"_vc":93},{"_i":"ms_005300.jpg","_t":5300,"_vc":94},{"_i":"ms_005400.jpg","_t":5400,"_vc":93},{"_i":"ms_005600.jpg","_t":5600,"_vc":94},{"_i":"ms_005800.jpg","_t":5800,"_vc":93},{"_i":"ms_006100.jpg","_t":6100,"_vc":97},{"_i":"ms_006200.jpg","_t":6200,"_vc":100}]],"visualComplete":[6200],"lighthouse":[31],"pagespeed":[75]}}