{"_ts":[1527837828],"_r":{"breakdown":{"html":{"bytes":[72854],"requests":[37]},"js":{"bytes":[734920],"requests":[49]},"css":{"bytes":[47882],"requests":[3]},"image":{"bytes":[647909],"requests":[72]},"flash":{"bytes":[0],"requests":[0]},"font":{"bytes":[0],"requests":[0]},"video":{"bytes":[0],"requests":[0]},"other":{"bytes":[9842],"requests":[53]}},"date":[1527837828],"domElements":[1718],"domInteractive":[1052],"firstPaint":[1050.4999999976],"fullyLoaded":[9230],"id":["180601_SD_14938f025ac147c8d586c667b3263118"],"loadTime":[2865],"render":[1100],"SpeedIndex":[1896],"TTFB":[231],"videoFrames":[[{"_i":"ms_000000.jpg","_t":0,"_vc":0},{"_i":"ms_001100.jpg","_t":1100,"_vc":48},{"_i":"ms_001500.jpg","_t":1500,"_vc":67},{"_i":"ms_001600.jpg","_t":1600,"_vc":67},{"_i":"ms_002000.jpg","_t":2000,"_vc":67},{"_i":"ms_002500.jpg","_t":2500,"_vc":92},{"_i":"ms_002800.jpg","_t":2800,"_vc":92},{"_i":"ms_003000.jpg","_t":3000,"_vc":92},{"_i":"ms_003200.jpg","_t":3200,"_vc":92},{"_i":"ms_003400.jpg","_t":3400,"_vc":82},{"_i":"ms_003800.jpg","_t":3800,"_vc":82},{"_i":"ms_003900.jpg","_t":3900,"_vc":82},{"_i":"ms_004000.jpg","_t":4000,"_vc":82},{"_i":"ms_004300.jpg","_t":4300,"_vc":88},{"_i":"ms_004500.jpg","_t":4500,"_vc":100}]],"visualComplete":[4500],"lighthouse":[45],"pagespeed":[66]}}